py_connect_4/__init__.py
py_connect_4/local.py
py_connect_4/main.py
py_connect_4/online/__init__.py
py_connect_4/online/client.py
py_connect_4/online/server.py
py_connect_4/online/utils.py
py_connect_4/utils.py
py_connect_4-0.1.2.dist-info/WHEEL
py_connect_4-0.1.2.dist-info/entry_points.txt
py_connect_4-0.1.2.dist-info/METADATA
py_connect_4-0.1.2.dist-info/RECORD
