Metadata-Version: 2.3
Name: py-connect-4
Version: 0.1.2
Summary: Play connect 4 in your terminal or online with your friends
Author: Jorge Gómez Zarzosa
Author-email: Jorge Gómez Zarzosa <jorge.gomzar@bmat.com>
Classifier: Environment :: Console
Classifier: Intended Audience :: Developers
Classifier: Operating System :: OS Independent
Classifier: Programming Language :: Python
Classifier: Programming Language :: Python :: 3.13
Classifier: Programming Language :: Python :: 3 :: Only
Classifier: Topic :: Games/Entertainment
Classifier: Topic :: Games/Entertainment :: Board Games
Requires-Dist: loguru>=0.7.3
Requires-Dist: numpy>=2.0.2
Requires-Dist: rich>=14.1.0
Requires-Python: >=3.13
